{
  "parent": "minecraft:recipes/root",
  "criteria": {
    "has_ender_bronze_chestplate": {
      "conditions": {
        "items": [
          {
            "items": [
              "better_progression:ender_bronze_chestplate"
            ]
          }
        ]
      },
      "trigger": "minecraft:inventory_changed"
    },
    "has_the_recipe": {
      "conditions": {
        "recipe": "better_progression:dragon_remains_from_smelting_bp_ender_bronze_chestplate"
      },
      "trigger": "minecraft:recipe_unlocked"
    }
  },
  "requirements": [
    [
      "has_ender_bronze_chestplate",
      "has_the_recipe"
    ]
  ],
  "rewards": {
    "recipes": [
      "better_progression:dragon_remains_from_smelting_bp_ender_bronze_chestplate"
    ]
  }
}